ratser/__init__.py
ratser/cli.py
ratser/intmap.py
ratser/trick.py
ratser/walimp.py
ratser-0.3.dist-info/METADATA
ratser-0.3.dist-info/WHEEL
ratser-0.3.dist-info/entry_points.txt
ratser-0.3.dist-info/top_level.txt
ratser-0.3.dist-info/RECORD
